.eslintrc
.prettierignore
.prettierrc.json
.stylelintignore
.stylelintrc.json
CHANGES.rst
CONTRIBUTORS.rst
Gruntfile.js
HOWTO_DEVELOP.rst
LICENSE
MANIFEST.in
README.rst
package-lock.json
package.json
publiccode.yml
setup.cfg
setup.py
docs/LICENSE.GPL
docs/LICENSE.rst
docs/index.rst
docs/migrationTo2.rst
src/design/__init__.py
src/design.plone.theme.egg-info/PKG-INFO
src/design.plone.theme.egg-info/SOURCES.txt
src/design.plone.theme.egg-info/dependency_links.txt
src/design.plone.theme.egg-info/entry_points.txt
src/design.plone.theme.egg-info/namespace_packages.txt
src/design.plone.theme.egg-info/not-zip-safe
src/design.plone.theme.egg-info/requires.txt
src/design.plone.theme.egg-info/top_level.txt
src/design/plone/__init__.py
src/design/plone/theme/__init__.py
src/design/plone/theme/configure.zcml
src/design/plone/theme/interfaces.py
src/design/plone/theme/monkey.py
src/design/plone/theme/setuphandlers.py
src/design/plone/theme/testing.py
src/design/plone/theme/vocabularies.py
src/design/plone/theme/behaviors/__init__.py
src/design/plone/theme/behaviors/behavior.py
src/design/plone/theme/behaviors/configure.zcml
src/design/plone/theme/browser/__init__.py
src/design/plone/theme/browser/configure.zcml
src/design/plone/theme/browser/main_template.py
src/design/plone/theme/browser/tile_collection_renderers.py
src/design/plone/theme/browser/tiles_page_view.py
src/design/plone/theme/browser/viewlets.py
src/design/plone/theme/browser/overrides/.gitkeep
src/design/plone/theme/browser/overrides/collective.editablemenu.browser.templates.custom_sections.pt
src/design/plone/theme/browser/overrides/plone.app.layout.viewlets.footer.pt
src/design/plone/theme/browser/overrides/plone.app.layout.viewlets.sections.pt
src/design/plone/theme/browser/overrides/plone.app.portlets.portlets.navigation_recurse.pt
src/design/plone/theme/browser/overrides/redturtle.tiles.management.browser.templates.tiles_view.pt
src/design/plone/theme/browser/static/.gitkeep
src/design/plone/theme/browser/static/plone-logged-in-compiled.min.js
src/design/plone/theme/browser/static/icons/avi.svg
src/design/plone/theme/browser/static/icons/default.svg
src/design/plone/theme/browser/static/icons/doc.svg
src/design/plone/theme/browser/static/icons/gif.svg
src/design/plone/theme/browser/static/icons/heic.svg
src/design/plone/theme/browser/static/icons/heif.svg
