Metadata-Version: 2.1
Name: design.plone.theme
Version: 6.0.5
Summary: Theme for Italia Design System
Home-page: https://github.com/italia/design.plone.theme.git
Author: RedTurtle
Author-email: sviluppoplone@redturtle.it
License: GPL version 3
Keywords: Plone Italia Design System Theme
Classifier: Environment :: Web Environment
Classifier: Framework :: Plone
Classifier: Framework :: Plone :: 5.0
Classifier: Framework :: Plone :: 5.1
Classifier: Framework :: Plone :: Theme
Classifier: Programming Language :: Python
Classifier: Programming Language :: Python :: 2.7
Classifier: Operating System :: OS Independent
Classifier: License :: OSI Approved :: GNU General Public License v3 (GPLv3)
Provides-Extra: test
License-File: LICENSE
